tailchart/__init__.py
tailchart/__main__.py
tailchart/index.html
tailchart/tailchart.py
tailchart-0.0.13.dist-info/DESCRIPTION.rst
tailchart-0.0.13.dist-info/METADATA
tailchart-0.0.13.dist-info/RECORD
tailchart-0.0.13.dist-info/WHEEL
tailchart-0.0.13.dist-info/entry_points.txt
tailchart-0.0.13.dist-info/metadata.json
tailchart-0.0.13.dist-info/top_level.txt
