Metadata-Version: 2.0
Name: tailchart
Version: 0.0.13
Summary: A CLI utility for charting data on the web.
Home-page: https://github.com/usbuild/tailchart
Author: Qichao Zhang
Author-email: njuzhangqichao@gmail.com
License: MIT
Platform: UNKNOWN
Classifier: Programming Language :: Python :: 2.6
Classifier: Programming Language :: Python :: 2.7
